MANIFEST.in
README.rst
setup.cfg
setup.py
bredala/__init__.py
bredala/decorations.py
bredala/modulehacker.py
bredala/signaturedecorator.py
bredala.egg-info/PKG-INFO
bredala.egg-info/SOURCES.txt
bredala.egg-info/dependency_links.txt
bredala.egg-info/requires.txt
bredala.egg-info/top_level.txt
bredala/demo/__init__.py
bredala/demo/myclasses.py
bredala/demo/myfunctions.py
bredala/test/t.py
bredala/test/test.py