Metadata-Version: 1.1
Name: bredala
Version: 1.0.1
Summary: .. image:: https://travis-ci.org/AGrigis/bredala.svg?branch=master
Home-page: http://github.com/AGrigis/bredala
Author: Antoine Grigis
Author-email: antoine.grigis@cea.fr
License: GPL 2+
Platform: any
Classifier: Intended Audience :: Developers
Classifier: License :: OSI Approved :: GNU General Public License v2 or later (GPLv2+)
Classifier: Operating System :: OS Independent
Classifier: Programming Language :: Python :: 2.7
Classifier: Programming Language :: Python :: 3
Classifier: Topic :: Software Development
